pyapp_flow/__init__.py
pyapp_flow/__main__.py
pyapp_flow/builtin/__init__.py
pyapp_flow/builtin/fs.py
pyapp_flow/builtin/tracking.py
pyapp_flow/cli/__init__.py
pyapp_flow/cli/actions.py
pyapp_flow/datastructures.py
pyapp_flow/default_settings.py
pyapp_flow/errors.py
pyapp_flow/ext/__init__.py
pyapp_flow/ext/pyapp/__init__.py
pyapp_flow/ext/sphinx/__init__.py
pyapp_flow/functions.py
pyapp_flow/helpers.py
pyapp_flow/nodes.py
pyapp_flow/parallel_nodes.py
pyapp_flow/steps.py
pyapp_flow/testing.py
pyapp_flow-0.20.2.dist-info/LICENSE
pyapp_flow-0.20.2.dist-info/METADATA
pyapp_flow-0.20.2.dist-info/WHEEL
pyapp_flow-0.20.2.dist-info/entry_points.txt
pyapp_flow-0.20.2.dist-info/RECORD
