Metadata-Version: 2.3
Name: pyapp-flow
Version: 0.20.2
Summary: Application workflow framework
License: BSD-3-Clause
Keywords: framework,application
Author: Tim Savage
Author-email: tim@savage.company
Requires-Python: ~=3.10
Classifier: Intended Audience :: Developers
Classifier: License :: OSI Approved :: BSD License
Classifier: Operating System :: OS Independent
Classifier: Development Status :: 4 - Beta
Classifier: Topic :: Software Development :: Libraries :: Python Modules
Classifier: Topic :: Software Development :: Libraries :: Application Frameworks
Classifier: Programming Language :: Python :: 3.10
Classifier: Programming Language :: Python :: 3.11
Classifier: Programming Language :: Python :: 3.12
Classifier: Programming Language :: Python :: 3.13
Classifier: Programming Language :: Python :: Implementation :: CPython
Requires-Dist: pyapp (>=4.10,<5.0)
Requires-Dist: rich (>=13.0)
Requires-Dist: typing-extensions (>=4.0,<5.0)
Project-URL: Repository, https://github.com/pyapp-org/pyapp-flow
